erabytse/__init__.py
erabytse/sweep.py
erabytse_sweep-0.1.0.dist-info/licenses/LICENSE
erabytse_sweep-0.1.0.dist-info/METADATA
erabytse_sweep-0.1.0.dist-info/WHEEL
erabytse_sweep-0.1.0.dist-info/entry_points.txt
erabytse_sweep-0.1.0.dist-info/top_level.txt
erabytse_sweep-0.1.0.dist-info/RECORD
