Metadata-Version: 2.4
Name: erabytse-sweep
Version: 0.1.0
Summary: A ritualistic tool to recycle digital clutter with intention.
Author-email: takouzlo <f.bfalik@gmail.com>
License: MIT
Classifier: License :: OSI Approved :: MIT License
Classifier: Programming Language :: Python :: 3
Classifier: Topic :: Utilities
Classifier: Intended Audience :: End Users/Desktop
Requires-Python: >=3.8
License-File: LICENSE
Dynamic: license-file
